kiara_plugin/tabular/__init__.py
kiara_plugin/tabular/defaults.py
kiara_plugin/tabular/py.typed
kiara_plugin/tabular/version.txt
kiara_plugin/tabular/data_types/__init__.py
kiara_plugin/tabular/data_types/array.py
kiara_plugin/tabular/data_types/db.py
kiara_plugin/tabular/data_types/table.py
kiara_plugin/tabular/data_types/tables.py
kiara_plugin/tabular/models/__init__.py
kiara_plugin/tabular/models/array.py
kiara_plugin/tabular/models/db.py
kiara_plugin/tabular/models/table.py
kiara_plugin/tabular/models/tables.py
kiara_plugin/tabular/modules/__init__.py
kiara_plugin/tabular/modules/array/__init__.py
kiara_plugin/tabular/modules/db/__init__.py
kiara_plugin/tabular/modules/table/__init__.py
kiara_plugin/tabular/modules/table/filters.py
kiara_plugin/tabular/modules/tables/__init__.py
kiara_plugin/tabular/pipelines/.gitkeep
kiara_plugin/tabular/pipelines/__init__.py
kiara_plugin/tabular/pipelines/extract_date_array.from.table.json
kiara_plugin/tabular/pipelines/import.database.from.local_file_path.json
kiara_plugin/tabular/pipelines/import.table.from.local_file_path.json
kiara_plugin/tabular/pipelines/import.table.from.local_folder_path.json
kiara_plugin/tabular/resources/.gitkeep
kiara_plugin/tabular/utils/__init__.py
kiara_plugin/tabular/utils/tables.py
kiara_plugin_tabular-0.5.7.dist-info/METADATA
kiara_plugin_tabular-0.5.7.dist-info/WHEEL
kiara_plugin_tabular-0.5.7.dist-info/entry_points.txt
kiara_plugin_tabular-0.5.7.dist-info/licenses/AUTHORS.md
kiara_plugin_tabular-0.5.7.dist-info/licenses/LICENSE
kiara_plugin_tabular-0.5.7.dist-info/RECORD
