Metadata-Version: 2.4
Name: kiara_plugin.tabular
Version: 0.5.7
Summary: Tabular data types and modules for kiara.
Project-URL: homepage, https://github.com/DHARPA-Project/kiara_plugin.tabular
Project-URL: documentation, https://DHARPA-Project.github.io/kiara_plugin.tabular
Project-URL: repository, https://github.com/DHARPA-Project/kiara_plugin.tabular
Author-email: Markus Binsteiner <markus@frkl.dev>
License: MPL-2.0
License-File: AUTHORS.md
License-File: LICENSE
Keywords: kiara,kiara-plugin
Classifier: Development Status :: 3 - Alpha
Classifier: License :: OSI Approved :: Mozilla Public License 2.0 (MPL 2.0)
Classifier: Programming Language :: Python
Classifier: Programming Language :: Python :: 3
Classifier: Programming Language :: Python :: 3 :: Only
Classifier: Programming Language :: Python :: 3.9
Classifier: Programming Language :: Python :: 3.10
Classifier: Programming Language :: Python :: 3.11
Classifier: Programming Language :: Python :: 3.12
Classifier: Programming Language :: Python :: 3.13
Requires-Python: >=3.9
Requires-Dist: duckdb>=1.1.0
Requires-Dist: kiara-plugin-core-types<0.6.0,>=0.5.2
Requires-Dist: kiara<0.6.0,>=0.5.15
Requires-Dist: numpy>=2.0.0
Requires-Dist: pandas>=2.0.0
Requires-Dist: polars>=0.18.0
Requires-Dist: pyarrow>=12.0.0
Requires-Dist: sqlalchemy-utc>=0.10.0
Requires-Dist: sqlalchemy-utils>=0.38.0
Requires-Dist: sqlalchemy>=2.0.0
Requires-Dist: sqlite-utils==3.30
Provides-Extra: jupyter
Requires-Dist: kiara[jupyter]; extra == 'jupyter'
Provides-Extra: marimo
Requires-Dist: kiara[marimo]; extra == 'marimo'
